{"items":[{"has_synonyms":false,"is_moderator_only":false,"is_required":false,"count":36,"name":"android-afilechooser"},{"has_synonyms":true,"is_moderator_only":false,"is_required":false,"count":33,"name":"android"},{"has_synonyms":true,"is_moderator_only":false,"is_required":false,"count":6,"name":"android-intent"},{"has_synonyms":false,"is_moderator_only":false,"is_required":false,"count":5,"name":"filechooser"},{"has_synonyms":true,"is_moderator_only":false,"is_required":false,"count":4,"name":"java"},{"has_synonyms":true,"is_moderator_only":false,"is_required":false,"count":3,"name":"android-studio"},{"has_synonyms":true,"is_moderator_only":false,"is_required":false,"count":2,"name":"file"},{"has_synonyms":true,"is_moderator_only":false,"is_required":false,"count":2,"name":"android-activity"},{"has_synonyms":false,"is_moderator_only":false,"is_required":false,"count":2,"name":"onactivityresult"},{"has_synonyms":true,"is_moderator_only":false,"is_required":false,"count":1,"name":"javascript"},{"has_synonyms":true,"is_moderator_only":false,"is_required":false,"count":1,"name":"git"},{"has_synonyms":false,"is_moderator_only":false,"is_required":false,"count":1,"name":"android-fragments"},{"has_synonyms":true,"is_moderator_only":false,"is_required":false,"count":1,"name":"web"},{"has_synonyms":true,"is_moderator_only":false,"is_required":false,"count":1,"name":"file-upload"},{"has_synonyms":false,"is_moderator_only":false,"is_required":false,"count":1,"name":"webview"},{"has_synonyms":true,"is_moderator_only":false,"is_required":false,"count":1,"name":"file-io"},{"has_synonyms":true,"is_moderator_only":false,"is_required":false,"count":1,"name":"view"},{"has_synonyms":true,"is_moderator_only":false,"is_required":false,"count":1,"name":"directory"},{"has_synonyms":true,"is_moderator_only":false,"is_required":false,"count":1,"name":"path"},{"has_synonyms":true,"is_moderator_only":false,"is_required":false,"count":1,"name":"gmail"},{"has_synonyms":false,"is_moderator_only":false,"is_required":false,"count":1,"name":"imageview"},{"has_synonyms":false,"is_moderator_only":false,"is_required":false,"count":1,"name":"android-webview"},{"has_synonyms":false,"is_moderator_only":false,"is_required":false,"count":1,"name":"uri"},{"has_synonyms":true,"is_moderator_only":false,"is_required":false,"count":1,"name":"emulation"},{"has_synonyms":false,"is_moderator_only":false,"is_required":false,"count":1,"name":"filepath"},{"has_synonyms":false,"is_moderator_only":false,"is_required":false,"count":1,"name":"noclassdeffounderror"},{"has_synonyms":true,"is_moderator_only":false,"is_required":false,"count":1,"name":"android-4.4-kitkat"},{"has_synonyms":false,"is_moderator_only":false,"is_required":false,"count":1,"name":"android-file"},{"has_synonyms":false,"is_moderator_only":false,"is_required":false,"count":1,"name":"google-drive-android-api"},{"has_synonyms":false,"is_moderator_only":false,"is_required":false,"count":1,"name":"storage-access-framework"},{"has_synonyms":false,"is_moderator_only":false,"is_required":false,"count":1,"name":"webviewclient"},{"has_synonyms":false,"is_moderator_only":false,"is_required":false,"count":1,"name":"webchromeclient"},{"has_synonyms":false,"is_moderator_only":false,"is_required":false,"count":1,"name":"android-implicit-intent"},{"has_synonyms":false,"is_moderator_only":false,"is_required":false,"count":1,"name":"cloudfiles"}],"has_more":false,"quota_max":10000,"quota_remaining":4930}