{"items":[{"has_synonyms":false,"is_moderator_only":false,"is_required":false,"count":52,"name":"catamorphism"},{"has_synonyms":false,"is_moderator_only":false,"is_required":false,"count":38,"name":"haskell"},{"has_synonyms":false,"is_moderator_only":false,"is_required":false,"count":26,"name":"recursion-schemes"},{"has_synonyms":true,"is_moderator_only":false,"is_required":false,"count":12,"name":"recursion"},{"has_synonyms":true,"is_moderator_only":false,"is_required":false,"count":11,"name":"functional-programming"},{"has_synonyms":false,"is_moderator_only":false,"is_required":false,"count":9,"name":"category-theory"},{"has_synonyms":true,"is_moderator_only":false,"is_required":false,"count":7,"name":"fold"},{"has_synonyms":true,"is_moderator_only":false,"is_required":false,"count":4,"name":"c#"},{"has_synonyms":false,"is_moderator_only":false,"is_required":false,"count":4,"name":"scala"},{"has_synonyms":true,"is_moderator_only":false,"is_required":false,"count":4,"name":"f#"},{"has_synonyms":true,"is_moderator_only":false,"is_required":false,"count":4,"name":"tree"},{"has_synonyms":true,"is_moderator_only":false,"is_required":false,"count":3,"name":"abstract-syntax-tree"},{"has_synonyms":false,"is_moderator_only":false,"is_required":false,"count":3,"name":"anamorphism"},{"has_synonyms":true,"is_moderator_only":false,"is_required":false,"count":2,"name":"optimization"},{"has_synonyms":false,"is_moderator_only":false,"is_required":false,"count":2,"name":"ghc"},{"has_synonyms":false,"is_moderator_only":false,"is_required":false,"count":2,"name":"algebraic-data-types"},{"has_synonyms":true,"is_moderator_only":false,"is_required":false,"count":2,"name":"fixpoint-combinators"},{"has_synonyms":true,"is_moderator_only":false,"is_required":false,"count":1,"name":"javascript"},{"has_synonyms":true,"is_moderator_only":false,"is_required":false,"count":1,"name":"reactjs"},{"has_synonyms":true,"is_moderator_only":false,"is_required":false,"count":1,"name":".net"},{"has_synonyms":true,"is_moderator_only":false,"is_required":false,"count":1,"name":"linq"},{"has_synonyms":true,"is_moderator_only":false,"is_required":false,"count":1,"name":"design-patterns"},{"has_synonyms":true,"is_moderator_only":false,"is_required":false,"count":1,"name":"types"},{"has_synonyms":true,"is_moderator_only":false,"is_required":false,"count":1,"name":"binary-search-tree"},{"has_synonyms":true,"is_moderator_only":false,"is_required":false,"count":1,"name":"monads"},{"has_synonyms":true,"is_moderator_only":false,"is_required":false,"count":1,"name":"lazy-evaluation"},{"has_synonyms":true,"is_moderator_only":false,"is_required":false,"count":1,"name":"type-inference"},{"has_synonyms":true,"is_moderator_only":false,"is_required":false,"count":1,"name":"sml"},{"has_synonyms":true,"is_moderator_only":false,"is_required":false,"count":1,"name":"typeclass"},{"has_synonyms":false,"is_moderator_only":false,"is_required":false,"count":1,"name":"composition"},{"has_synonyms":false,"is_moderator_only":false,"is_required":false,"count":1,"name":"tail-recursion"},{"has_synonyms":false,"is_moderator_only":false,"is_required":false,"count":1,"name":"scalaz"},{"has_synonyms":false,"is_moderator_only":false,"is_required":false,"count":1,"name":"composite"},{"has_synonyms":false,"is_moderator_only":false,"is_required":false,"count":1,"name":"algebra"},{"has_synonyms":false,"is_moderator_only":false,"is_required":false,"count":1,"name":"tree-traversal"},{"has_synonyms":false,"is_moderator_only":false,"is_required":false,"count":1,"name":"agda"},{"has_synonyms":false,"is_moderator_only":false,"is_required":false,"count":1,"name":"purescript"},{"has_synonyms":true,"is_moderator_only":false,"is_required":false,"count":1,"name":"type-systems"},{"has_synonyms":false,"is_moderator_only":false,"is_required":false,"count":1,"name":"kdtree"},{"has_synonyms":false,"is_moderator_only":false,"is_required":false,"count":1,"name":"gadt"},{"has_synonyms":false,"is_moderator_only":false,"is_required":false,"count":1,"name":"conditional-rendering"},{"has_synonyms":false,"is_moderator_only":false,"is_required":false,"count":1,"name":"fusion"},{"has_synonyms":false,"is_moderator_only":false,"is_required":false,"count":1,"name":"scala-option"},{"has_synonyms":false,"is_moderator_only":false,"is_required":false,"count":1,"name":"mutual-recursion"},{"has_synonyms":false,"is_moderator_only":false,"is_required":false,"count":1,"name":"church-encoding"},{"has_synonyms":false,"is_moderator_only":false,"is_required":false,"count":1,"name":"foldable"},{"has_synonyms":false,"is_moderator_only":false,"is_required":false,"count":1,"name":"comonad"},{"has_synonyms":false,"is_moderator_only":false,"is_required":false,"count":1,"name":"fantasyland"}],"has_more":false,"quota_max":10000,"quota_remaining":9014}