{"items":[{"has_synonyms":true,"is_moderator_only":false,"is_required":false,"count":13,"name":"r"},{"has_synonyms":false,"is_moderator_only":false,"is_required":false,"count":13,"name":"ggtitle"},{"has_synonyms":true,"is_moderator_only":false,"is_required":false,"count":12,"name":"ggplot2"},{"has_synonyms":true,"is_moderator_only":false,"is_required":false,"count":1,"name":"list"},{"has_synonyms":true,"is_moderator_only":false,"is_required":false,"count":1,"name":"function"},{"has_synonyms":true,"is_moderator_only":false,"is_required":false,"count":1,"name":"loops"},{"has_synonyms":true,"is_moderator_only":false,"is_required":false,"count":1,"name":"plot"},{"has_synonyms":true,"is_moderator_only":false,"is_required":false,"count":1,"name":"shiny"},{"has_synonyms":true,"is_moderator_only":false,"is_required":false,"count":1,"name":"fonts"},{"has_synonyms":true,"is_moderator_only":false,"is_required":false,"count":1,"name":"themes"},{"has_synonyms":true,"is_moderator_only":false,"is_required":false,"count":1,"name":"expression"},{"has_synonyms":true,"is_moderator_only":false,"is_required":false,"count":1,"name":"bar-chart"},{"has_synonyms":false,"is_moderator_only":false,"is_required":false,"count":1,"name":"lapply"},{"has_synonyms":false,"is_moderator_only":false,"is_required":false,"count":1,"name":"center"},{"has_synonyms":true,"is_moderator_only":false,"is_required":false,"count":1,"name":"line-breaks"},{"has_synonyms":false,"is_moderator_only":false,"is_required":false,"count":1,"name":"geom-text"},{"has_synonyms":false,"is_moderator_only":false,"is_required":false,"count":1,"name":"scale-color-manual"}],"has_more":false,"quota_max":10000,"quota_remaining":9779}