{"items":[{"has_synonyms":false,"is_moderator_only":false,"is_required":false,"count":31,"name":"gsmcomm"},{"has_synonyms":true,"is_moderator_only":false,"is_required":false,"count":19,"name":"c#"},{"has_synonyms":true,"is_moderator_only":false,"is_required":false,"count":11,"name":"sms"},{"has_synonyms":true,"is_moderator_only":false,"is_required":false,"count":9,"name":"at-command"},{"has_synonyms":false,"is_moderator_only":false,"is_required":false,"count":8,"name":"gsm"},{"has_synonyms":false,"is_moderator_only":false,"is_required":false,"count":4,"name":"pdu"},{"has_synonyms":true,"is_moderator_only":false,"is_required":false,"count":3,"name":"winforms"},{"has_synonyms":true,"is_moderator_only":false,"is_required":false,"count":2,"name":"java"},{"has_synonyms":true,"is_moderator_only":false,"is_required":false,"count":2,"name":"asp.net"},{"has_synonyms":true,"is_moderator_only":false,"is_required":false,"count":2,"name":"oracle11g"},{"has_synonyms":true,"is_moderator_only":false,"is_required":false,"count":2,"name":"serial-port"},{"has_synonyms":false,"is_moderator_only":false,"is_required":false,"count":2,"name":"ussd"},{"has_synonyms":false,"is_moderator_only":false,"is_required":false,"count":2,"name":"sim900"},{"has_synonyms":true,"is_moderator_only":false,"is_required":false,"count":1,"name":"android"},{"has_synonyms":false,"is_moderator_only":false,"is_required":false,"count":1,"name":"linux"},{"has_synonyms":true,"is_moderator_only":false,"is_required":false,"count":1,"name":"visual-studio"},{"has_synonyms":true,"is_moderator_only":false,"is_required":false,"count":1,"name":"web"},{"has_synonyms":false,"is_moderator_only":false,"is_required":false,"count":1,"name":"error-handling"},{"has_synonyms":false,"is_moderator_only":false,"is_required":false,"count":1,"name":"arduino"},{"has_synonyms":false,"is_moderator_only":false,"is_required":false,"count":1,"name":"mono"},{"has_synonyms":true,"is_moderator_only":false,"is_required":false,"count":1,"name":"embedded"},{"has_synonyms":true,"is_moderator_only":false,"is_required":false,"count":1,"name":"report"},{"has_synonyms":false,"is_moderator_only":false,"is_required":false,"count":1,"name":"devexpress"},{"has_synonyms":false,"is_moderator_only":false,"is_required":false,"count":1,"name":"iot"},{"has_synonyms":false,"is_moderator_only":false,"is_required":false,"count":1,"name":"messaging"},{"has_synonyms":false,"is_moderator_only":false,"is_required":false,"count":1,"name":"arduino-uno"},{"has_synonyms":false,"is_moderator_only":false,"is_required":false,"count":1,"name":"esp32"},{"has_synonyms":false,"is_moderator_only":false,"is_required":false,"count":1,"name":"status"},{"has_synonyms":false,"is_moderator_only":false,"is_required":false,"count":1,"name":"sendmessage"},{"has_synonyms":false,"is_moderator_only":false,"is_required":false,"count":1,"name":"modem"},{"has_synonyms":false,"is_moderator_only":false,"is_required":false,"count":1,"name":"smsmanager"},{"has_synonyms":false,"is_moderator_only":false,"is_required":false,"count":1,"name":"lte"},{"has_synonyms":false,"is_moderator_only":false,"is_required":false,"count":1,"name":"4g"},{"has_synonyms":false,"is_moderator_only":false,"is_required":false,"count":1,"name":"qualcomm"},{"has_synonyms":false,"is_moderator_only":false,"is_required":false,"count":1,"name":"quectel"}],"has_more":false,"quota_max":10000,"quota_remaining":2966}