{"items":[{"has_synonyms":false,"is_moderator_only":false,"is_required":false,"count":128,"name":"highlight.js"},{"has_synonyms":true,"is_moderator_only":false,"is_required":false,"count":60,"name":"javascript"},{"has_synonyms":false,"is_moderator_only":false,"is_required":false,"count":29,"name":"syntax-highlighting"},{"has_synonyms":true,"is_moderator_only":false,"is_required":false,"count":25,"name":"html"},{"has_synonyms":true,"is_moderator_only":false,"is_required":false,"count":17,"name":"jquery"},{"has_synonyms":true,"is_moderator_only":false,"is_required":false,"count":14,"name":"css"},{"has_synonyms":true,"is_moderator_only":false,"is_required":false,"count":13,"name":"highlight"},{"has_synonyms":true,"is_moderator_only":false,"is_required":false,"count":10,"name":"reactjs"},{"has_synonyms":true,"is_moderator_only":false,"is_required":false,"count":9,"name":"angularjs"},{"has_synonyms":false,"is_moderator_only":false,"is_required":false,"count":8,"name":"reveal.js"},{"has_synonyms":false,"is_moderator_only":false,"is_required":false,"count":5,"name":"ckeditor"},{"has_synonyms":false,"is_moderator_only":false,"is_required":false,"count":5,"name":"markdown"},{"has_synonyms":true,"is_moderator_only":false,"is_required":false,"count":4,"name":"angular"},{"has_synonyms":true,"is_moderator_only":false,"is_required":false,"count":4,"name":"quill"},{"has_synonyms":true,"is_moderator_only":false,"is_required":false,"count":3,"name":"ruby-on-rails"},{"has_synonyms":true,"is_moderator_only":false,"is_required":false,"count":3,"name":"typescript"},{"has_synonyms":true,"is_moderator_only":false,"is_required":false,"count":3,"name":"ember.js"},{"has_synonyms":true,"is_moderator_only":false,"is_required":false,"count":2,"name":"php"},{"has_synonyms":true,"is_moderator_only":false,"is_required":false,"count":2,"name":"r"},{"has_synonyms":true,"is_moderator_only":false,"is_required":false,"count":2,"name":"node.js"},{"has_synonyms":true,"is_moderator_only":false,"is_required":false,"count":2,"name":"regex"},{"has_synonyms":true,"is_moderator_only":false,"is_required":false,"count":2,"name":"ajax"},{"has_synonyms":true,"is_moderator_only":false,"is_required":false,"count":2,"name":"vue.js"},{"has_synonyms":true,"is_moderator_only":false,"is_required":false,"count":2,"name":"web"},{"has_synonyms":true,"is_moderator_only":false,"is_required":false,"count":2,"name":"knockout.js"},{"has_synonyms":false,"is_moderator_only":false,"is_required":false,"count":2,"name":"syntax"},{"has_synonyms":false,"is_moderator_only":false,"is_required":false,"count":2,"name":"angularjs-directive"},{"has_synonyms":false,"is_moderator_only":false,"is_required":false,"count":2,"name":"frontend"},{"has_synonyms":false,"is_moderator_only":false,"is_required":false,"count":2,"name":"cdn"},{"has_synonyms":false,"is_moderator_only":false,"is_required":false,"count":2,"name":"hugo"},{"has_synonyms":false,"is_moderator_only":false,"is_required":false,"count":2,"name":"syntaxhighlighter"},{"has_synonyms":false,"is_moderator_only":false,"is_required":false,"count":2,"name":"tiddlywiki"},{"has_synonyms":false,"is_moderator_only":false,"is_required":false,"count":2,"name":"showdown"},{"has_synonyms":false,"is_moderator_only":false,"is_required":false,"count":2,"name":"markdown-it"},{"has_synonyms":false,"is_moderator_only":false,"is_required":false,"count":2,"name":"react-syntax-highlighter"},{"has_synonyms":true,"is_moderator_only":false,"is_required":false,"count":1,"name":"ios"},{"has_synonyms":true,"is_moderator_only":false,"is_required":false,"count":1,"name":"json"},{"has_synonyms":true,"is_moderator_only":false,"is_required":false,"count":1,"name":"swift"},{"has_synonyms":true,"is_moderator_only":false,"is_required":false,"count":1,"name":"vb.net"},{"has_synonyms":true,"is_moderator_only":false,"is_required":false,"count":1,"name":"react-native"},{"has_synonyms":true,"is_moderator_only":false,"is_required":false,"count":1,"name":"twitter-bootstrap"},{"has_synonyms":true,"is_moderator_only":false,"is_required":false,"count":1,"name":"ruby-on-rails-3"},{"has_synonyms":false,"is_moderator_only":false,"is_required":false,"count":1,"name":"jsp"},{"has_synonyms":true,"is_moderator_only":false,"is_required":false,"count":1,"name":"templates"},{"has_synonyms":false,"is_moderator_only":false,"is_required":false,"count":1,"name":"heroku"},{"has_synonyms":true,"is_moderator_only":false,"is_required":false,"count":1,"name":"npm"},{"has_synonyms":false,"is_moderator_only":false,"is_required":false,"count":1,"name":"jquery-ui"},{"has_synonyms":true,"is_moderator_only":false,"is_required":false,"count":1,"name":"svg"},{"has_synonyms":false,"is_moderator_only":false,"is_required":false,"count":1,"name":"webpack"},{"has_synonyms":false,"is_moderator_only":false,"is_required":false,"count":1,"name":"ruby-on-rails-4"}],"has_more":false,"quota_max":10000,"quota_remaining":9771}