{"items":[{"has_synonyms":false,"is_moderator_only":false,"is_required":false,"count":558,"name":"jqgrid-asp.net"},{"has_synonyms":true,"is_moderator_only":false,"is_required":false,"count":425,"name":"jqgrid"},{"has_synonyms":true,"is_moderator_only":false,"is_required":false,"count":213,"name":"jquery"},{"has_synonyms":true,"is_moderator_only":false,"is_required":false,"count":96,"name":"asp.net-mvc"},{"has_synonyms":true,"is_moderator_only":false,"is_required":false,"count":72,"name":"asp.net"},{"has_synonyms":true,"is_moderator_only":false,"is_required":false,"count":64,"name":"javascript"},{"has_synonyms":false,"is_moderator_only":false,"is_required":false,"count":60,"name":"jqgrid-formatter"},{"has_synonyms":true,"is_moderator_only":false,"is_required":false,"count":44,"name":"c#"},{"has_synonyms":true,"is_moderator_only":false,"is_required":false,"count":41,"name":"asp.net-mvc-3"},{"has_synonyms":false,"is_moderator_only":false,"is_required":false,"count":39,"name":"mvcjqgrid"},{"has_synonyms":true,"is_moderator_only":false,"is_required":false,"count":24,"name":"asp.net-mvc-4"},{"has_synonyms":false,"is_moderator_only":false,"is_required":false,"count":20,"name":"jqgrid-php"},{"has_synonyms":true,"is_moderator_only":false,"is_required":false,"count":19,"name":"json"},{"has_synonyms":false,"is_moderator_only":false,"is_required":false,"count":17,"name":"jquery-ui"},{"has_synonyms":true,"is_moderator_only":false,"is_required":false,"count":12,"name":"jquery-plugins"},{"has_synonyms":false,"is_moderator_only":false,"is_required":false,"count":12,"name":"jqgrid-inlinenav"},{"has_synonyms":false,"is_moderator_only":false,"is_required":false,"count":11,"name":"free-jqgrid"},{"has_synonyms":true,"is_moderator_only":false,"is_required":false,"count":10,"name":"asp.net-mvc-2"},{"has_synonyms":true,"is_moderator_only":false,"is_required":false,"count":7,"name":"webforms"},{"has_synonyms":true,"is_moderator_only":false,"is_required":false,"count":6,"name":"entity-framework"},{"has_synonyms":true,"is_moderator_only":false,"is_required":false,"count":5,"name":"ajax"},{"has_synonyms":true,"is_moderator_only":false,"is_required":false,"count":5,"name":"web-services"},{"has_synonyms":true,"is_moderator_only":false,"is_required":false,"count":5,"name":"model-view-controller"},{"has_synonyms":true,"is_moderator_only":false,"is_required":false,"count":5,"name":"pagination"},{"has_synonyms":true,"is_moderator_only":false,"is_required":false,"count":4,"name":"html"},{"has_synonyms":true,"is_moderator_only":false,"is_required":false,"count":4,"name":"css"},{"has_synonyms":true,"is_moderator_only":false,"is_required":false,"count":4,"name":".net"},{"has_synonyms":true,"is_moderator_only":false,"is_required":false,"count":4,"name":"search"},{"has_synonyms":false,"is_moderator_only":false,"is_required":false,"count":4,"name":"subgrid"},{"has_synonyms":true,"is_moderator_only":false,"is_required":false,"count":3,"name":"linq"},{"has_synonyms":false,"is_moderator_only":false,"is_required":false,"count":3,"name":"asp.net-web-api"},{"has_synonyms":true,"is_moderator_only":false,"is_required":false,"count":3,"name":"razor"},{"has_synonyms":true,"is_moderator_only":false,"is_required":false,"count":3,"name":"entity-framework-4"},{"has_synonyms":true,"is_moderator_only":false,"is_required":false,"count":2,"name":"sql-server"},{"has_synonyms":true,"is_moderator_only":false,"is_required":false,"count":2,"name":"xml"},{"has_synonyms":true,"is_moderator_only":false,"is_required":false,"count":2,"name":"checkbox"},{"has_synonyms":false,"is_moderator_only":false,"is_required":false,"count":2,"name":"c#-4.0"},{"has_synonyms":true,"is_moderator_only":false,"is_required":false,"count":2,"name":"visual-studio-2013"},{"has_synonyms":true,"is_moderator_only":false,"is_required":false,"count":2,"name":"asp.net-mvc-5"},{"has_synonyms":false,"is_moderator_only":false,"is_required":false,"count":2,"name":"grid"},{"has_synonyms":true,"is_moderator_only":false,"is_required":false,"count":2,"name":"linq-to-entities"},{"has_synonyms":true,"is_moderator_only":false,"is_required":false,"count":2,"name":"lazy-loading"},{"has_synonyms":true,"is_moderator_only":false,"is_required":false,"count":2,"name":"toolbar"},{"has_synonyms":false,"is_moderator_only":false,"is_required":false,"count":2,"name":"export-to-excel"},{"has_synonyms":false,"is_moderator_only":false,"is_required":false,"count":2,"name":"pager"},{"has_synonyms":true,"is_moderator_only":false,"is_required":false,"count":1,"name":"sql"},{"has_synonyms":true,"is_moderator_only":false,"is_required":false,"count":1,"name":"database"},{"has_synonyms":true,"is_moderator_only":false,"is_required":false,"count":1,"name":"vb.net"},{"has_synonyms":true,"is_moderator_only":false,"is_required":false,"count":1,"name":"visual-studio"},{"has_synonyms":true,"is_moderator_only":false,"is_required":false,"count":1,"name":"twitter-bootstrap"}],"has_more":false,"quota_max":10000,"quota_remaining":1915}