{"items":[{"has_synonyms":false,"is_moderator_only":false,"is_required":false,"count":27,"name":"odatacontroller"},{"has_synonyms":false,"is_moderator_only":false,"is_required":false,"count":26,"name":"odata"},{"has_synonyms":false,"is_moderator_only":false,"is_required":false,"count":9,"name":"asp.net-web-api"},{"has_synonyms":true,"is_moderator_only":false,"is_required":false,"count":5,"name":"entity-framework"},{"has_synonyms":false,"is_moderator_only":false,"is_required":false,"count":5,"name":"asp.net-web-api2"},{"has_synonyms":true,"is_moderator_only":false,"is_required":false,"count":4,"name":"c#"},{"has_synonyms":true,"is_moderator_only":false,"is_required":false,"count":2,"name":"kendo-ui"},{"has_synonyms":false,"is_moderator_only":false,"is_required":false,"count":2,"name":"kendo-grid"},{"has_synonyms":false,"is_moderator_only":false,"is_required":false,"count":2,"name":"asp.net-apicontroller"},{"has_synonyms":true,"is_moderator_only":false,"is_required":false,"count":1,"name":"javascript"},{"has_synonyms":true,"is_moderator_only":false,"is_required":false,"count":1,"name":"asp.net"},{"has_synonyms":true,"is_moderator_only":false,"is_required":false,"count":1,"name":".net"},{"has_synonyms":true,"is_moderator_only":false,"is_required":false,"count":1,"name":"angularjs"},{"has_synonyms":true,"is_moderator_only":false,"is_required":false,"count":1,"name":"excel"},{"has_synonyms":true,"is_moderator_only":false,"is_required":false,"count":1,"name":"ajax"},{"has_synonyms":true,"is_moderator_only":false,"is_required":false,"count":1,"name":"asp.net-mvc"},{"has_synonyms":true,"is_moderator_only":false,"is_required":false,"count":1,"name":"vb.net"},{"has_synonyms":true,"is_moderator_only":false,"is_required":false,"count":1,"name":"api"},{"has_synonyms":true,"is_moderator_only":false,"is_required":false,"count":1,"name":"rest"},{"has_synonyms":true,"is_moderator_only":false,"is_required":false,"count":1,"name":"linq"},{"has_synonyms":true,"is_moderator_only":false,"is_required":false,"count":1,"name":"authentication"},{"has_synonyms":true,"is_moderator_only":false,"is_required":false,"count":1,"name":"exception"},{"has_synonyms":true,"is_moderator_only":false,"is_required":false,"count":1,"name":"routes"},{"has_synonyms":true,"is_moderator_only":false,"is_required":false,"count":1,"name":"controller"},{"has_synonyms":false,"is_moderator_only":false,"is_required":false,"count":1,"name":"powerbi"},{"has_synonyms":true,"is_moderator_only":false,"is_required":false,"count":1,"name":"asp.net-core-mvc"},{"has_synonyms":true,"is_moderator_only":false,"is_required":false,"count":1,"name":"entity-framework-6"},{"has_synonyms":true,"is_moderator_only":false,"is_required":false,"count":1,"name":"authorization"},{"has_synonyms":false,"is_moderator_only":false,"is_required":false,"count":1,"name":"ef-code-first"},{"has_synonyms":true,"is_moderator_only":false,"is_required":false,"count":1,"name":"webclient"},{"has_synonyms":true,"is_moderator_only":false,"is_required":false,"count":1,"name":"data-modeling"},{"has_synonyms":false,"is_moderator_only":false,"is_required":false,"count":1,"name":"asp.net-core-3.1"},{"has_synonyms":true,"is_moderator_only":false,"is_required":false,"count":1,"name":"mongodb-.net-driver"},{"has_synonyms":false,"is_moderator_only":false,"is_required":false,"count":1,"name":"restsharp"},{"has_synonyms":false,"is_moderator_only":false,"is_required":false,"count":1,"name":"url-parameters"},{"has_synonyms":false,"is_moderator_only":false,"is_required":false,"count":1,"name":"asp.net-web-api-routing"},{"has_synonyms":false,"is_moderator_only":false,"is_required":false,"count":1,"name":"atom-feed"},{"has_synonyms":false,"is_moderator_only":false,"is_required":false,"count":1,"name":"attributerouting"},{"has_synonyms":false,"is_moderator_only":false,"is_required":false,"count":1,"name":"jaydata"},{"has_synonyms":false,"is_moderator_only":false,"is_required":false,"count":1,"name":"odata-v4"},{"has_synonyms":false,"is_moderator_only":false,"is_required":false,"count":1,"name":"asp.net-web-api-odata"},{"has_synonyms":false,"is_moderator_only":false,"is_required":false,"count":1,"name":"servicecontract"},{"has_synonyms":false,"is_moderator_only":false,"is_required":false,"count":1,"name":"notimplementedexception"},{"has_synonyms":false,"is_moderator_only":false,"is_required":false,"count":1,"name":"odatalib"},{"has_synonyms":false,"is_moderator_only":false,"is_required":false,"count":1,"name":"webchannelfactory"}],"has_more":false,"quota_max":10000,"quota_remaining":1580}