{"items":[{"has_synonyms":false,"is_moderator_only":false,"is_required":false,"count":132,"name":"payment-method"},{"has_synonyms":false,"is_moderator_only":false,"is_required":false,"count":79,"name":"woocommerce"},{"has_synonyms":true,"is_moderator_only":false,"is_required":false,"count":76,"name":"php"},{"has_synonyms":true,"is_moderator_only":false,"is_required":false,"count":72,"name":"wordpress"},{"has_synonyms":false,"is_moderator_only":false,"is_required":false,"count":20,"name":"checkout"},{"has_synonyms":false,"is_moderator_only":false,"is_required":false,"count":15,"name":"payment-gateway"},{"has_synonyms":true,"is_moderator_only":false,"is_required":false,"count":13,"name":"magento"},{"has_synonyms":true,"is_moderator_only":false,"is_required":false,"count":12,"name":"payment"},{"has_synonyms":false,"is_moderator_only":false,"is_required":false,"count":12,"name":"orders"},{"has_synonyms":true,"is_moderator_only":false,"is_required":false,"count":10,"name":"paypal"},{"has_synonyms":false,"is_moderator_only":false,"is_required":false,"count":10,"name":"magento2"},{"has_synonyms":false,"is_moderator_only":false,"is_required":false,"count":10,"name":"hook-woocommerce"},{"has_synonyms":false,"is_moderator_only":false,"is_required":false,"count":7,"name":"magento-1.9"},{"has_synonyms":true,"is_moderator_only":false,"is_required":false,"count":6,"name":"stripe-payments"},{"has_synonyms":false,"is_moderator_only":false,"is_required":false,"count":6,"name":"cart"},{"has_synonyms":false,"is_moderator_only":false,"is_required":false,"count":6,"name":"braintree"},{"has_synonyms":false,"is_moderator_only":false,"is_required":false,"count":5,"name":"email-notifications"},{"has_synonyms":false,"is_moderator_only":false,"is_required":false,"count":5,"name":"shipping-method"},{"has_synonyms":true,"is_moderator_only":false,"is_required":false,"count":3,"name":"jquery"},{"has_synonyms":false,"is_moderator_only":false,"is_required":false,"count":3,"name":"laravel"},{"has_synonyms":true,"is_moderator_only":false,"is_required":false,"count":3,"name":"e-commerce"},{"has_synonyms":false,"is_moderator_only":false,"is_required":false,"count":3,"name":"shipping"},{"has_synonyms":true,"is_moderator_only":false,"is_required":false,"count":2,"name":"javascript"},{"has_synonyms":true,"is_moderator_only":false,"is_required":false,"count":2,"name":"ios"},{"has_synonyms":false,"is_moderator_only":false,"is_required":false,"count":2,"name":"curl"},{"has_synonyms":false,"is_moderator_only":false,"is_required":false,"count":2,"name":"opencart"},{"has_synonyms":true,"is_moderator_only":false,"is_required":false,"count":2,"name":"customization"},{"has_synonyms":true,"is_moderator_only":false,"is_required":false,"count":2,"name":"credit-card"},{"has_synonyms":false,"is_moderator_only":false,"is_required":false,"count":2,"name":"applepay"},{"has_synonyms":false,"is_moderator_only":false,"is_required":false,"count":2,"name":"fee"},{"has_synonyms":true,"is_moderator_only":false,"is_required":false,"count":1,"name":"java"},{"has_synonyms":true,"is_moderator_only":false,"is_required":false,"count":1,"name":"css"},{"has_synonyms":true,"is_moderator_only":false,"is_required":false,"count":1,"name":"mysql"},{"has_synonyms":true,"is_moderator_only":false,"is_required":false,"count":1,"name":"node.js"},{"has_synonyms":true,"is_moderator_only":false,"is_required":false,"count":1,"name":"reactjs"},{"has_synonyms":true,"is_moderator_only":false,"is_required":false,"count":1,"name":"swift"},{"has_synonyms":true,"is_moderator_only":false,"is_required":false,"count":1,"name":"ajax"},{"has_synonyms":true,"is_moderator_only":false,"is_required":false,"count":1,"name":"asp.net-mvc"},{"has_synonyms":false,"is_moderator_only":false,"is_required":false,"count":1,"name":"selenium"},{"has_synonyms":true,"is_moderator_only":false,"is_required":false,"count":1,"name":"validation"},{"has_synonyms":true,"is_moderator_only":false,"is_required":false,"count":1,"name":"web"},{"has_synonyms":false,"is_moderator_only":false,"is_required":false,"count":1,"name":"post"},{"has_synonyms":true,"is_moderator_only":false,"is_required":false,"count":1,"name":"redirect"},{"has_synonyms":true,"is_moderator_only":false,"is_required":false,"count":1,"name":"checkbox"},{"has_synonyms":false,"is_moderator_only":false,"is_required":false,"count":1,"name":"soap"},{"has_synonyms":true,"is_moderator_only":false,"is_required":false,"count":1,"name":"types"},{"has_synonyms":true,"is_moderator_only":false,"is_required":false,"count":1,"name":"plugins"},{"has_synonyms":true,"is_moderator_only":false,"is_required":false,"count":1,"name":"eloquent"},{"has_synonyms":false,"is_moderator_only":false,"is_required":false,"count":1,"name":"joomla"},{"has_synonyms":false,"is_moderator_only":false,"is_required":false,"count":1,"name":"sdk"}],"has_more":false,"quota_max":10000,"quota_remaining":1226}