{"items":[{"has_synonyms":true,"is_moderator_only":false,"is_required":false,"count":16,"name":"ibm-cloud"},{"has_synonyms":false,"is_moderator_only":false,"is_required":false,"count":16,"name":"presenceinsights"},{"has_synonyms":false,"is_moderator_only":false,"is_required":false,"count":3,"name":"ibeacon"},{"has_synonyms":false,"is_moderator_only":false,"is_required":false,"count":2,"name":"analytics"},{"has_synonyms":false,"is_moderator_only":false,"is_required":false,"count":2,"name":"indoor-positioning-system"},{"has_synonyms":true,"is_moderator_only":false,"is_required":false,"count":1,"name":"javascript"},{"has_synonyms":true,"is_moderator_only":false,"is_required":false,"count":1,"name":"ajax"},{"has_synonyms":true,"is_moderator_only":false,"is_required":false,"count":1,"name":"deployment"},{"has_synonyms":false,"is_moderator_only":false,"is_required":false,"count":1,"name":"server"},{"has_synonyms":false,"is_moderator_only":false,"is_required":false,"count":1,"name":"swagger"},{"has_synonyms":false,"is_moderator_only":false,"is_required":false,"count":1,"name":"location"},{"has_synonyms":true,"is_moderator_only":false,"is_required":false,"count":1,"name":"wifi"},{"has_synonyms":true,"is_moderator_only":false,"is_required":false,"count":1,"name":"instance"},{"has_synonyms":false,"is_moderator_only":false,"is_required":false,"count":1,"name":"node-red"},{"has_synonyms":false,"is_moderator_only":false,"is_required":false,"count":1,"name":"raspberry-pi2"},{"has_synonyms":false,"is_moderator_only":false,"is_required":false,"count":1,"name":"beacon"},{"has_synonyms":false,"is_moderator_only":false,"is_required":false,"count":1,"name":"connector"},{"has_synonyms":true,"is_moderator_only":false,"is_required":false,"count":1,"name":"demo"},{"has_synonyms":false,"is_moderator_only":false,"is_required":false,"count":1,"name":"estimote"},{"has_synonyms":false,"is_moderator_only":false,"is_required":false,"count":1,"name":"sample-data"},{"has_synonyms":false,"is_moderator_only":false,"is_required":false,"count":1,"name":"data-export"}],"has_more":false,"quota_max":10000,"quota_remaining":4556}