{"items":[{"has_synonyms":false,"is_moderator_only":false,"is_required":false,"count":236,"name":"rc"},{"has_synonyms":false,"is_moderator_only":false,"is_required":false,"count":43,"name":"linux"},{"has_synonyms":true,"is_moderator_only":false,"is_required":false,"count":34,"name":"bash"},{"has_synonyms":true,"is_moderator_only":false,"is_required":false,"count":29,"name":"python"},{"has_synonyms":true,"is_moderator_only":false,"is_required":false,"count":19,"name":"shell"},{"has_synonyms":true,"is_moderator_only":false,"is_required":false,"count":17,"name":"c++"},{"has_synonyms":false,"is_moderator_only":false,"is_required":false,"count":16,"name":"selenium"},{"has_synonyms":true,"is_moderator_only":false,"is_required":false,"count":13,"name":"resources"},{"has_synonyms":true,"is_moderator_only":false,"is_required":false,"count":12,"name":"windows"},{"has_synonyms":false,"is_moderator_only":false,"is_required":false,"count":12,"name":"startup"},{"has_synonyms":true,"is_moderator_only":false,"is_required":false,"count":10,"name":"ubuntu"},{"has_synonyms":true,"is_moderator_only":false,"is_required":false,"count":10,"name":"delphi"},{"has_synonyms":true,"is_moderator_only":false,"is_required":false,"count":9,"name":"winapi"},{"has_synonyms":false,"is_moderator_only":false,"is_required":false,"count":8,"name":"raspberry-pi"},{"has_synonyms":false,"is_moderator_only":false,"is_required":false,"count":8,"name":"init"},{"has_synonyms":false,"is_moderator_only":false,"is_required":false,"count":8,"name":"boot"},{"has_synonyms":true,"is_moderator_only":false,"is_required":false,"count":7,"name":"c#"},{"has_synonyms":true,"is_moderator_only":false,"is_required":false,"count":7,"name":"visual-studio"},{"has_synonyms":true,"is_moderator_only":false,"is_required":false,"count":7,"name":"matplotlib"},{"has_synonyms":false,"is_moderator_only":false,"is_required":false,"count":7,"name":"raspbian"},{"has_synonyms":false,"is_moderator_only":false,"is_required":false,"count":7,"name":"freebsd"},{"has_synonyms":false,"is_moderator_only":false,"is_required":false,"count":6,"name":"rust"},{"has_synonyms":false,"is_moderator_only":false,"is_required":false,"count":6,"name":"mfc"},{"has_synonyms":true,"is_moderator_only":false,"is_required":false,"count":5,"name":"php"},{"has_synonyms":true,"is_moderator_only":false,"is_required":false,"count":5,"name":"xpath"},{"has_synonyms":true,"is_moderator_only":false,"is_required":false,"count":5,"name":"vim"},{"has_synonyms":false,"is_moderator_only":false,"is_required":false,"count":5,"name":"arduino"},{"has_synonyms":false,"is_moderator_only":false,"is_required":false,"count":5,"name":"configuration"},{"has_synonyms":false,"is_moderator_only":false,"is_required":false,"count":5,"name":"refcell"},{"has_synonyms":true,"is_moderator_only":false,"is_required":false,"count":4,"name":"android"},{"has_synonyms":true,"is_moderator_only":false,"is_required":false,"count":4,"name":"node.js"},{"has_synonyms":true,"is_moderator_only":false,"is_required":false,"count":4,"name":"angular"},{"has_synonyms":false,"is_moderator_only":false,"is_required":false,"count":4,"name":"cmake"},{"has_synonyms":true,"is_moderator_only":false,"is_required":false,"count":4,"name":"visual-studio-2015"},{"has_synonyms":false,"is_moderator_only":false,"is_required":false,"count":4,"name":"autostart"},{"has_synonyms":false,"is_moderator_only":false,"is_required":false,"count":4,"name":"init.d"},{"has_synonyms":true,"is_moderator_only":false,"is_required":false,"count":3,"name":"javascript"},{"has_synonyms":true,"is_moderator_only":false,"is_required":false,"count":3,"name":"java"},{"has_synonyms":false,"is_moderator_only":false,"is_required":false,"count":3,"name":"c"},{"has_synonyms":true,"is_moderator_only":false,"is_required":false,"count":3,"name":"python-3.x"},{"has_synonyms":true,"is_moderator_only":false,"is_required":false,"count":3,"name":"visual-studio-2010"},{"has_synonyms":false,"is_moderator_only":false,"is_required":false,"count":3,"name":"junit"},{"has_synonyms":true,"is_moderator_only":false,"is_required":false,"count":3,"name":"dialog"},{"has_synonyms":true,"is_moderator_only":false,"is_required":false,"count":3,"name":"pid"},{"has_synonyms":true,"is_moderator_only":false,"is_required":false,"count":2,"name":"r"},{"has_synonyms":true,"is_moderator_only":false,"is_required":false,"count":2,"name":"macos"},{"has_synonyms":true,"is_moderator_only":false,"is_required":false,"count":2,"name":"maven"},{"has_synonyms":true,"is_moderator_only":false,"is_required":false,"count":2,"name":"unit-testing"},{"has_synonyms":false,"is_moderator_only":false,"is_required":false,"count":2,"name":"curl"},{"has_synonyms":true,"is_moderator_only":false,"is_required":false,"count":2,"name":"visual-studio-code"}],"has_more":false,"quota_max":10000,"quota_remaining":6400}