{"items":[{"has_synonyms":false,"is_moderator_only":false,"is_required":false,"count":234,"name":"reply"},{"has_synonyms":true,"is_moderator_only":false,"is_required":false,"count":40,"name":"email"},{"has_synonyms":true,"is_moderator_only":false,"is_required":false,"count":39,"name":"php"},{"has_synonyms":true,"is_moderator_only":false,"is_required":false,"count":31,"name":"comments"},{"has_synonyms":true,"is_moderator_only":false,"is_required":false,"count":25,"name":"python"},{"has_synonyms":true,"is_moderator_only":false,"is_required":false,"count":23,"name":"outlook"},{"has_synonyms":false,"is_moderator_only":false,"is_required":false,"count":18,"name":"request"},{"has_synonyms":true,"is_moderator_only":false,"is_required":false,"count":16,"name":"twitter"},{"has_synonyms":true,"is_moderator_only":false,"is_required":false,"count":13,"name":"vba"},{"has_synonyms":true,"is_moderator_only":false,"is_required":false,"count":12,"name":"javascript"},{"has_synonyms":true,"is_moderator_only":false,"is_required":false,"count":11,"name":"wordpress"},{"has_synonyms":true,"is_moderator_only":false,"is_required":false,"count":10,"name":"c#"},{"has_synonyms":true,"is_moderator_only":false,"is_required":false,"count":10,"name":"forms"},{"has_synonyms":true,"is_moderator_only":false,"is_required":false,"count":8,"name":"gmail"},{"has_synonyms":true,"is_moderator_only":false,"is_required":false,"count":8,"name":"bots"},{"has_synonyms":true,"is_moderator_only":false,"is_required":false,"count":7,"name":"button"},{"has_synonyms":false,"is_moderator_only":false,"is_required":false,"count":7,"name":"jms"},{"has_synonyms":true,"is_moderator_only":false,"is_required":false,"count":5,"name":"html"},{"has_synonyms":true,"is_moderator_only":false,"is_required":false,"count":5,"name":"jquery"},{"has_synonyms":true,"is_moderator_only":false,"is_required":false,"count":5,"name":"mysql"},{"has_synonyms":true,"is_moderator_only":false,"is_required":false,"count":5,"name":"excel"},{"has_synonyms":true,"is_moderator_only":false,"is_required":false,"count":5,"name":"api"},{"has_synonyms":false,"is_moderator_only":false,"is_required":false,"count":5,"name":"gmail-api"},{"has_synonyms":true,"is_moderator_only":false,"is_required":false,"count":5,"name":"zeromq"},{"has_synonyms":true,"is_moderator_only":false,"is_required":false,"count":4,"name":"node.js"},{"has_synonyms":false,"is_moderator_only":false,"is_required":false,"count":4,"name":"c"},{"has_synonyms":true,"is_moderator_only":false,"is_required":false,"count":4,"name":"ruby-on-rails"},{"has_synonyms":true,"is_moderator_only":false,"is_required":false,"count":4,"name":"facebook"},{"has_synonyms":true,"is_moderator_only":false,"is_required":false,"count":4,"name":"sockets"},{"has_synonyms":false,"is_moderator_only":false,"is_required":false,"count":4,"name":"post"},{"has_synonyms":true,"is_moderator_only":false,"is_required":false,"count":4,"name":"facebook-graph-api"},{"has_synonyms":false,"is_moderator_only":false,"is_required":false,"count":4,"name":"twilio"},{"has_synonyms":true,"is_moderator_only":false,"is_required":false,"count":4,"name":"message"},{"has_synonyms":false,"is_moderator_only":false,"is_required":false,"count":4,"name":"tweepy"},{"has_synonyms":true,"is_moderator_only":false,"is_required":false,"count":4,"name":"forum"},{"has_synonyms":true,"is_moderator_only":false,"is_required":false,"count":3,"name":"c++"},{"has_synonyms":true,"is_moderator_only":false,"is_required":false,"count":3,"name":"ios"},{"has_synonyms":true,"is_moderator_only":false,"is_required":false,"count":3,"name":"asp.net"},{"has_synonyms":false,"is_moderator_only":false,"is_required":false,"count":3,"name":"django"},{"has_synonyms":true,"is_moderator_only":false,"is_required":false,"count":3,"name":"powershell"},{"has_synonyms":false,"is_moderator_only":false,"is_required":false,"count":3,"name":"http"},{"has_synonyms":true,"is_moderator_only":false,"is_required":false,"count":3,"name":"search"},{"has_synonyms":true,"is_moderator_only":false,"is_required":false,"count":3,"name":"header"},{"has_synonyms":true,"is_moderator_only":false,"is_required":false,"count":3,"name":"apache-camel"},{"has_synonyms":false,"is_moderator_only":false,"is_required":false,"count":3,"name":"mule"},{"has_synonyms":false,"is_moderator_only":false,"is_required":false,"count":3,"name":"vsto"},{"has_synonyms":false,"is_moderator_only":false,"is_required":false,"count":3,"name":"phpmailer"},{"has_synonyms":true,"is_moderator_only":false,"is_required":false,"count":3,"name":"system"},{"has_synonyms":true,"is_moderator_only":false,"is_required":false,"count":3,"name":"ibm-mq"},{"has_synonyms":false,"is_moderator_only":false,"is_required":false,"count":3,"name":"sendgrid"}],"has_more":false,"quota_max":10000,"quota_remaining":6327}