{"items":[{"has_synonyms":false,"is_moderator_only":false,"is_required":false,"count":810,"name":"sequential"},{"has_synonyms":true,"is_moderator_only":false,"is_required":false,"count":133,"name":"python"},{"has_synonyms":false,"is_moderator_only":false,"is_required":false,"count":106,"name":"keras"},{"has_synonyms":true,"is_moderator_only":false,"is_required":false,"count":59,"name":"java"},{"has_synonyms":true,"is_moderator_only":false,"is_required":false,"count":59,"name":"tensorflow"},{"has_synonyms":true,"is_moderator_only":false,"is_required":false,"count":55,"name":"javascript"},{"has_synonyms":true,"is_moderator_only":false,"is_required":false,"count":41,"name":"r"},{"has_synonyms":true,"is_moderator_only":false,"is_required":false,"count":40,"name":"jquery"},{"has_synonyms":true,"is_moderator_only":false,"is_required":false,"count":32,"name":"c++"},{"has_synonyms":true,"is_moderator_only":false,"is_required":false,"count":30,"name":"sql"},{"has_synonyms":true,"is_moderator_only":false,"is_required":false,"count":30,"name":"arrays"},{"has_synonyms":true,"is_moderator_only":false,"is_required":false,"count":27,"name":"neural-network"},{"has_synonyms":true,"is_moderator_only":false,"is_required":false,"count":24,"name":"search"},{"has_synonyms":true,"is_moderator_only":false,"is_required":false,"count":22,"name":"c#"},{"has_synonyms":true,"is_moderator_only":false,"is_required":false,"count":22,"name":"file"},{"has_synonyms":true,"is_moderator_only":false,"is_required":false,"count":21,"name":"php"},{"has_synonyms":true,"is_moderator_only":false,"is_required":false,"count":20,"name":"deep-learning"},{"has_synonyms":true,"is_moderator_only":false,"is_required":false,"count":19,"name":"loops"},{"has_synonyms":true,"is_moderator_only":false,"is_required":false,"count":19,"name":"parallel-processing"},{"has_synonyms":false,"is_moderator_only":false,"is_required":false,"count":17,"name":"c"},{"has_synonyms":true,"is_moderator_only":false,"is_required":false,"count":17,"name":"conv-neural-network"},{"has_synonyms":true,"is_moderator_only":false,"is_required":false,"count":16,"name":"mysql"},{"has_synonyms":true,"is_moderator_only":false,"is_required":false,"count":16,"name":"list"},{"has_synonyms":true,"is_moderator_only":false,"is_required":false,"count":16,"name":"asynchronous"},{"has_synonyms":false,"is_moderator_only":false,"is_required":false,"count":15,"name":"vhdl"},{"has_synonyms":true,"is_moderator_only":false,"is_required":false,"count":14,"name":"android"},{"has_synonyms":true,"is_moderator_only":false,"is_required":false,"count":14,"name":"node.js"},{"has_synonyms":true,"is_moderator_only":false,"is_required":false,"count":14,"name":"sql-server"},{"has_synonyms":false,"is_moderator_only":false,"is_required":false,"count":14,"name":"lstm"},{"has_synonyms":false,"is_moderator_only":false,"is_required":false,"count":14,"name":"verilog"},{"has_synonyms":true,"is_moderator_only":false,"is_required":false,"count":13,"name":"multithreading"},{"has_synonyms":true,"is_moderator_only":false,"is_required":false,"count":13,"name":"algorithm"},{"has_synonyms":true,"is_moderator_only":false,"is_required":false,"count":12,"name":"bash"},{"has_synonyms":true,"is_moderator_only":false,"is_required":false,"count":12,"name":"matlab"},{"has_synonyms":false,"is_moderator_only":false,"is_required":false,"count":12,"name":"machine-learning"},{"has_synonyms":false,"is_moderator_only":false,"is_required":false,"count":12,"name":"promise"},{"has_synonyms":false,"is_moderator_only":false,"is_required":false,"count":11,"name":"pandas"},{"has_synonyms":true,"is_moderator_only":false,"is_required":false,"count":11,"name":"animation"},{"has_synonyms":true,"is_moderator_only":false,"is_required":false,"count":11,"name":"concurrency"},{"has_synonyms":true,"is_moderator_only":false,"is_required":false,"count":11,"name":"recurrent-neural-network"},{"has_synonyms":true,"is_moderator_only":false,"is_required":false,"count":10,"name":"python-3.x"},{"has_synonyms":true,"is_moderator_only":false,"is_required":false,"count":10,"name":"sorting"},{"has_synonyms":true,"is_moderator_only":false,"is_required":false,"count":10,"name":"batch-file"},{"has_synonyms":false,"is_moderator_only":false,"is_required":false,"count":10,"name":"pytorch"},{"has_synonyms":true,"is_moderator_only":false,"is_required":false,"count":9,"name":"excel"},{"has_synonyms":true,"is_moderator_only":false,"is_required":false,"count":9,"name":"dataframe"},{"has_synonyms":true,"is_moderator_only":false,"is_required":false,"count":9,"name":"for-loop"},{"has_synonyms":true,"is_moderator_only":false,"is_required":false,"count":9,"name":"numbers"},{"has_synonyms":false,"is_moderator_only":false,"is_required":false,"count":8,"name":"oracle"},{"has_synonyms":false,"is_moderator_only":false,"is_required":false,"count":8,"name":"scala"}],"has_more":false,"quota_max":10000,"quota_remaining":3776}