{"items":[{"has_synonyms":true,"is_moderator_only":false,"is_required":false,"count":1,"name":"java"},{"has_synonyms":false,"is_moderator_only":false,"is_required":false,"count":1,"name":"eclipse"},{"has_synonyms":true,"is_moderator_only":false,"is_required":false,"count":1,"name":"jakarta-ee"},{"has_synonyms":false,"is_moderator_only":false,"is_required":false,"count":1,"name":"servlet-4"},{"has_synonyms":false,"is_moderator_only":false,"is_required":false,"count":1,"name":"servlet-5.0"}],"has_more":false,"quota_max":10000,"quota_remaining":2311}