{"items":[{"has_synonyms":false,"is_moderator_only":false,"is_required":false,"count":17,"name":"sunpkcs11"},{"has_synonyms":true,"is_moderator_only":false,"is_required":false,"count":13,"name":"java"},{"has_synonyms":true,"is_moderator_only":false,"is_required":false,"count":9,"name":"pkcs#11"},{"has_synonyms":false,"is_moderator_only":false,"is_required":false,"count":6,"name":"hsm"},{"has_synonyms":false,"is_moderator_only":false,"is_required":false,"count":3,"name":"jce"},{"has_synonyms":false,"is_moderator_only":false,"is_required":false,"count":2,"name":"keystore"},{"has_synonyms":false,"is_moderator_only":false,"is_required":false,"count":2,"name":"softhsm"},{"has_synonyms":true,"is_moderator_only":false,"is_required":false,"count":1,"name":"amazon-web-services"},{"has_synonyms":false,"is_moderator_only":false,"is_required":false,"count":1,"name":"spring-boot"},{"has_synonyms":true,"is_moderator_only":false,"is_required":false,"count":1,"name":"authentication"},{"has_synonyms":false,"is_moderator_only":false,"is_required":false,"count":1,"name":"digital-signature"},{"has_synonyms":true,"is_moderator_only":false,"is_required":false,"count":1,"name":"java-11"},{"has_synonyms":true,"is_moderator_only":false,"is_required":false,"count":1,"name":"signature"},{"has_synonyms":true,"is_moderator_only":false,"is_required":false,"count":1,"name":"java-9"},{"has_synonyms":true,"is_moderator_only":false,"is_required":false,"count":1,"name":"32-bit"},{"has_synonyms":false,"is_moderator_only":false,"is_required":false,"count":1,"name":"keytool"},{"has_synonyms":false,"is_moderator_only":false,"is_required":false,"count":1,"name":"java-security"},{"has_synonyms":false,"is_moderator_only":false,"is_required":false,"count":1,"name":"fips"},{"has_synonyms":false,"is_moderator_only":false,"is_required":false,"count":1,"name":"jca"},{"has_synonyms":false,"is_moderator_only":false,"is_required":false,"count":1,"name":"nss"},{"has_synonyms":false,"is_moderator_only":false,"is_required":false,"count":1,"name":"ecdh"},{"has_synonyms":false,"is_moderator_only":false,"is_required":false,"count":1,"name":"opensc"},{"has_synonyms":false,"is_moderator_only":false,"is_required":false,"count":1,"name":"iaik-jce"},{"has_synonyms":false,"is_moderator_only":false,"is_required":false,"count":1,"name":"amazon-cloudhsm"}],"has_more":false,"quota_max":10000,"quota_remaining":4771}